cf_lines_overlap-0.0.1.dist-info/DESCRIPTION.rst
cf_lines_overlap-0.0.1.dist-info/METADATA
cf_lines_overlap-0.0.1.dist-info/RECORD
cf_lines_overlap-0.0.1.dist-info/WHEEL
cf_lines_overlap-0.0.1.dist-info/metadata.json
cf_lines_overlap-0.0.1.dist-info/top_level.txt
overlap/__init__.py
overlap/overlap.py
