Metadata-Version: 2.0
Name: cf-lines-overlap
Version: 0.0.1
Summary: Check if 2 lines overlap
Home-page: https://github.com/carlos-ferras/code-challenge/overlap
Author: Carlos Ferras
Author-email: c4rlos.ferra5@gmail.com
License: MIT
Platform: UNKNOWN
